{"is_source_file": true, "format": "TypeScript declaration file (.d.ts)", "description": "This file defines global namespace augmentations for a SvelteKit application, setting up potential interfaces for error handling, locals, page data, page state, and platform, but currently all are commented out.", "external_files": ["https://svelte.dev/docs/kit/types#app.d.ts"], "external_methods": [], "published": [], "classes": [], "methods": [], "calls": [], "search-terms": ["SvelteKit", "TypeScript declaration", "global namespace", "app.d.ts", "interfaces", "augmentations"], "state": 2, "file_id": 7, "knowledge_revision": 25, "git_revision": "3681ca217674644fee4886750c39ee108ee0607c", "ctags": [{"_type": "tag", "name": "App", "path": "/home/kavia/workspace/code-generation/flappy-bird-clone-fe3d8600/flappy_bird_frontend/src/app.d.ts", "pattern": "/^\tnamespace App {$/", "language": "TypeScript", "kind": "namespace"}], "hash": "78b56494b3f78d7f9bacda13678f159e", "format-version": 4, "code-base-name": "flappy_bird_frontend", "filename": "flappy_bird_frontend/src/app.d.ts", "revision_history": [{"25": "3681ca217674644fee4886750c39ee108ee0607c"}]}